toUpper.v
`timescale 1ns / 1ps

module toUpper(a,b);
    input [7:0] a;
    output [7:0] b;

    wire na7, na6, na4, na3, na2, na1, na0;
    wire t1, t2, t3, t4, t5;
    
    not #5 (na7, a[7]); 
    not #5 (na6, a[6]);
    not #5 (na4, a[4]);
    not #5 (na3, a[3]);
    not #5 (na2, a[2]);
    not #5 (na1, a[1]);
    not #5 (na0, a[0]);

    and #10 (t1, a[7], a[6]);
    and #10 (t2, na7, na6, a[5]);
    and #10 (t3, na7, a[6], a[5], a[4], a[3],a[2]);
    and #10 (t4, na7, a[6], a[5],a[4],a[3],na2,a[1],a[0]);
    and #10 (t5, na7, a[5], na4, na3, na2, na1, na0);

    or #10 (b[5],t1,t2,t3,t4,t5);

    buf #4 (b[0], a[0]);
    buf #4 (b[1], a[1]);
    buf #4 (b[2], a[2]);
    buf #4 (b[3], a[3]);
    buf #4 (b[4], a[4]);
    buf #4 (b[6], a[6]);
    buf #4 (b[7], a[7]);

endmodule

tb_toUpper.v
`timescale 1ns/1ps

module tb_toUpper;

reg [7:0] a;
wire [7:0] b;

toUpper dut (.a(a), .b(b));

initial begin
    $dumpfile("toUpper.vcd");
    $dumpvars(0, tb_toUpper);
    
    // (
    {a[7],a[6],a[5],a[4],a[3],a[2],a[1],a[0]} = 8'b00101000; #26;
    // H
    {a[7],a[6],a[5],a[4],a[3],a[2],a[1],a[0]} = 8'b01001000; #26;
    // .
    {a[7],a[6],a[5],a[4],a[3],a[2],a[1],a[0]} = 8'b10110111; #26;
    // f
    {a[7],a[6],a[5],a[4],a[3],a[2],a[1],a[0]} = 8'b10000011; #26;
    // |
    {a[7],a[6],a[5],a[4],a[3],a[2],a[1],a[0]} = 8'b01111100; #26;
    // DC4
    {a[7],a[6],a[5],a[4],a[3],a[2],a[1],a[0]} = 8'b00010100; #26;
    // ë
    {a[7],a[6],a[5],a[4],a[3],a[2],a[1],a[0]} = 8'b11101011; #26;
    // a
    {a[7],a[6],a[5],a[4],a[3],a[2],a[1],a[0]} = 8'b01100001; #26;
    // A
    {a[7],a[6],a[5],a[4],a[3],a[2],a[1],a[0]} = 8'b01000001; #26;
    // z
    {a[7],a[6],a[5],a[4],a[3],a[2],a[1],a[0]} = 8'b01111010; #26;
    // G
    {a[7],a[6],a[5],a[4],a[3],a[2],a[1],a[0]} = 8'b01000111; #26;
    // m
    {a[7],a[6],a[5],a[4],a[3],a[2],a[1],a[0]} = 8'b01101101; #26;
    // '
    {a[7],a[6],a[5],a[4],a[3],a[2],a[1],a[0]} = 8'b10010010; #26;
    // 0
    {a[7],a[6],a[5],a[4],a[3],a[2],a[1],a[0]} = 8'b00110000; #26;
    // Ï
    {a[7],a[6],a[5],a[4],a[3],a[2],a[1],a[0]} = 8'b11001111; #26;
    // : 
    {a[7],a[6],a[5],a[4],a[3],a[2],a[1],a[0]} = 8'b00111010; #26;
    // {
    {a[7],a[6],a[5],a[4],a[3],a[2],a[1],a[0]} = 8'b01111011; #26;
    // ”
    {a[7],a[6],a[5],a[4],a[3],a[2],a[1],a[0]} = 8'b10010100; #26;
    // DEL
    {a[7],a[6],a[5],a[4],a[3],a[2],a[1],a[0]} = 8'b01111111; #26;

    #50 $finish;
end

endmodule

toUpper.vcd
$date
	Thu Nov  6 14:55:34 2025
$end
$version
	Icarus Verilog
$end
$timescale
	1ps
$end
$scope module tb_toUpper $end
$var wire 8 ! b [7:0] $end
$var reg 8 " a [7:0] $end
$scope module dut $end
$var wire 8 # a [7:0] $end
$var wire 1 $ na0 $end
$var wire 1 % na1 $end
$var wire 1 & na2 $end
$var wire 1 ' na3 $end
$var wire 1 ( na4 $end
$var wire 1 ) na6 $end
$var wire 1 * na7 $end
$var wire 1 + t1 $end
$var wire 1 , t2 $end
$var wire 1 - t3 $end
$var wire 1 . t4 $end
$var wire 1 / t5 $end
$var wire 8 0 b [7:0] $end
$upscope $end
$upscope $end
$enddefinitions $end
$comment Show the parameter values. $end
$dumpall
$end
#0
$dumpvars
bx 0
x/
x.
x-
x,
x+
x*
x)
x(
x'
x&
x%
x$
b101000 #
b101000 "
bx !
$end
#4000
b0x01000 !
b0x01000 0
#5000
1*
1)
1(
0'
1&
1%
1$
#10000
0-
0.
0+
#15000
0/
1,
#25000
b101000 !
b101000 0
#26000
b1001000 "
b1001000 #
#30000
b1101000 !
b1101000 0
#31000
0)
#36000
0,
#46000
b1001000 !
b1001000 0
#52000
b10110111 "
b10110111 #
#56000
b10010111 !
b10010111 0
#57000
0*
1)
0(
1'
0&
0%
0$
#78000
b10000011 "
b10000011 #
#82000
b10000011 !
b10000011 0
#83000
1(
1&
#104000
b1111100 "
b1111100 #
#108000
b1011100 !
b1011100 0
#109000
1*
0)
0(
0'
0&
1%
1$
#119000
1-
#129000
b1111100 !
b1111100 0
#130000
b10100 "
b10100 #
#134000
b110100 !
b110100 0
#135000
1)
1'
#140000
0-
#150000
b10100 !
b10100 0
#156000
b11101011 "
b11101011 #
#160000
b11001011 !
b11001011 0
#161000
0*
0)
1(
0'
1&
0%
0$
#166000
1+
#176000
b11101011 !
b11101011 0
#182000
b1100001 "
b1100001 #
#186000
b1100001 !
b1100001 0
#187000
1*
1'
1%
#192000
0+
#202000
b1000001 !
b1000001 0
#208000
b1000001 "
b1000001 #
#234000
b1111010 "
b1111010 #
#238000
b1011010 !
b1011010 0
#239000
0(
0'
0%
1$
#260000
b1000111 "
b1000111 #
#264000
b1000111 !
b1000111 0
#265000
1(
1'
0&
0$
#286000
b1101101 "
b1101101 #
#290000
b1001101 !
b1001101 0
#291000
0'
1%
#312000
b10010010 "
b10010010 #
#316000
b10010010 !
b10010010 0
#317000
0*
1)
0(
1'
1&
0%
1$
#338000
b110000 "
b110000 #
#342000
b10000 !
b10000 0
#343000
1*
1%
#353000
1,
#363000
b110000 !
b110000 0
#364000
b11001111 "
b11001111 #
#368000
b11101111 !
b11101111 0
#369000
0*
0)
1(
0'
0&
0%
0$
#374000
1+
0,
#390000
b111010 "
b111010 #
#394000
b111010 !
b111010 0
#395000
1*
1)
0(
1&
1$
#400000
0+
#405000
1,
#416000
b1111011 "
b1111011 #
#420000
b1111011 !
b1111011 0
#421000
0)
0$
#426000
1.
#431000
0,
#442000
b10010100 "
b10010100 #
#446000
b10110100 !
b10110100 0
#447000
0*
1)
1'
0&
1%
1$
#452000
0.
#462000
b10010100 !
b10010100 0
#468000
b1111111 "
b1111111 #
#472000
b1011111 !
b1011111 0
#473000
1*
0)
0'
0%
0$
#483000
1-
#493000
b1111111 !
b1111111 0
