toUpper.v
`timescale 1ns / 1ps

module toUpper (a,b);
    input  [7:0] a;
    output [7:0] b;

    wire na7, na6, na4, na3, na2, na1, na0;
    wire t1, t2, t3, t4;
    wire sum;
    wire simplified, notsimplified;

    not #5 (na7, a[7]);
    not #5 (na6, a[6]);
    not #5 (na4, a[4]);
    not #5 (na3, a[3]);
    not #5 (na2, a[2]);
    not #5 (na1, a[1]);
    not #5 (na0, a[0]);

    and #10 (t1, na7, a[6], a[5], na4, (a[3] | a[2] | a[1] | a[0]));
    and #10 (t2, na7, a[6], a[5], a[4], na3);
    and #10 (t3, na7, a[6], a[5], a[4], a[3], na2);
    and #10 (t4, na7, a[6], a[5], a[4], a[3], a[2], na1, na0);

    or #10 (sum, t1, t2, t3, t4);

    and #10 (simplified, sum, a[5]);
    not #5 (notsimplified, simplified);
    and #10 (b[5], a[5], notsimplified);

    buf #4 (b[0], a[0]);
    buf #4 (b[1], a[1]);
    buf #4 (b[2], a[2]);
    buf #4 (b[3], a[3]);
    buf #4 (b[4], a[4]);
    buf #4 (b[6], a[6]);
    buf #4 (b[7], a[7]);
endmodule

tb_toUpper.v
module tb_toUpper;

reg [7:0] a;
wire [7:0] b;

toUpper dut (.a(a), .b(b));

initial begin
    $dumpfile("toUpper.vcd");
    $dumpvars(0, tb_toUpper);
    
    // (
    {a[7],a[6],a[5],a[4],a[3],a[2],a[1],a[0]} = 8'b00101000; #15;
    // H
    {a[7],a[6],a[5],a[4],a[3],a[2],a[1],a[0]} = 8'b01001000; #15;
    // .
    {a[7],a[6],a[5],a[4],a[3],a[2],a[1],a[0]} = 8'b10110111; #15;
    // f
    {a[7],a[6],a[5],a[4],a[3],a[2],a[1],a[0]} = 8'b10000011; #15;
    // |
    {a[7],a[6],a[5],a[4],a[3],a[2],a[1],a[0]} = 8'b01111100; #15;
    // DC4
    {a[7],a[6],a[5],a[4],a[3],a[2],a[1],a[0]} = 8'b00010100; #15;
    // ë
    {a[7],a[6],a[5],a[4],a[3],a[2],a[1],a[0]} = 8'b11101011; #15;
    // a
    {a[7],a[6],a[5],a[4],a[3],a[2],a[1],a[0]} = 8'b01100001; #15;
    // A
    {a[7],a[6],a[5],a[4],a[3],a[2],a[1],a[0]} = 8'b01000001; #15;
    // z
    {a[7],a[6],a[5],a[4],a[3],a[2],a[1],a[0]} = 8'b01111010; #15;
    // G
    {a[7],a[6],a[5],a[4],a[3],a[2],a[1],a[0]} = 8'b01000111; #15;
    // m
    {a[7],a[6],a[5],a[4],a[3],a[2],a[1],a[0]} = 8'b01101101; #15;
    // '
    {a[7],a[6],a[5],a[4],a[3],a[2],a[1],a[0]} = 8'b10010010; #15;
    // 0
    {a[7],a[6],a[5],a[4],a[3],a[2],a[1],a[0]} = 8'b00110000; #15;
    // Ï
    {a[7],a[6],a[5],a[4],a[3],a[2],a[1],a[0]} = 8'b11001111; #15;
    // : 
    {a[7],a[6],a[5],a[4],a[3],a[2],a[1],a[0]} = 8'b00111010; #15;
    // {
    {a[7],a[6],a[5],a[4],a[3],a[2],a[1],a[0]} = 8'b01111011; #15;
    // ”
    {a[7],a[6],a[5],a[4],a[3],a[2],a[1],a[0]} = 8'b10010100; #15;
    // DEL
    {a[7],a[6],a[5],a[4],a[3],a[2],a[1],a[0]} = 8'b01111111; #15;

    #50 $finish;
end

endmodule

toUpper.vcd
$date
	Tue Nov  4 23:18:57 2025
$end
$version
	Icarus Verilog
$end
$timescale
	1ps
$end
$scope module tb_toUpper $end
$var wire 8 ! b [7:0] $end
$var reg 8 " a [7:0] $end
$scope module dut $end
$var wire 8 # a [7:0] $end
$var wire 1 $ na0 $end
$var wire 1 % na1 $end
$var wire 1 & na2 $end
$var wire 1 ' na3 $end
$var wire 1 ( na4 $end
$var wire 1 ) na6 $end
$var wire 1 * na7 $end
$var wire 1 + notsimplified $end
$var wire 1 , simplified $end
$var wire 1 - sum $end
$var wire 1 . t1 $end
$var wire 1 / t2 $end
$var wire 1 0 t3 $end
$var wire 1 1 t4 $end
$var wire 8 2 b [7:0] $end
$upscope $end
$upscope $end
$enddefinitions $end
$comment Show the parameter values. $end
$dumpall
$end
#0
$dumpvars
bx 2
x1
x0
x/
x.
x-
x,
x+
x*
x)
x(
x'
x&
x%
x$
b101000 #
b101000 "
bx !
$end
#4000
b0x01000 !
b0x01000 2
#5000
1*
1)
1(
0'
1&
1%
1$
#10000
0.
0/
00
01
#20000
0-
#30000
0,
#35000
1+
#45000
b101000 !
b101000 2
#15000000000000
b1001000 "
b1001000 #
#15000000004000
b1101000 !
b1101000 2
#15000000005000
0)
#15000000010000
b1001000 !
b1001000 2
#30000000000000
b10110111 "
b10110111 #
#30000000004000
b10010111 !
b10010111 2
#30000000005000
0*
1)
0(
1'
0&
0%
0$
#30000000010000
b10110111 !
b10110111 2
#45000000000000
b10000011 "
b10000011 #
#45000000004000
b10100011 !
b10100011 2
#45000000005000
1(
1&
#45000000010000
b10000011 !
b10000011 2
#60000000000000
b1111100 "
b1111100 #
#60000000004000
b1011100 !
b1011100 2
#60000000005000
1*
0)
0(
0'
0&
1%
1$
#60000000010000
b1111100 !
b1111100 2
#60000000015000
11
#60000000025000
1-
#60000000035000
1,
#60000000040000
0+
#60000000050000
b1011100 !
b1011100 2
#75000000000000
b10100 "
b10100 #
#75000000004000
b10100 !
b10100 2
#75000000005000
1)
1'
#75000000010000
01
0,
#75000000015000
1+
#75000000020000
0-
#90000000000000
b11101011 "
b11101011 #
#90000000004000
b11001011 !
b11001011 2
#90000000005000
0*
0)
1(
0'
1&
0%
0$
#90000000010000
b11101011 !
b11101011 2
#105000000000000
b1100001 "
b1100001 #
#105000000004000
b1100001 !
b1100001 2
#105000000005000
1*
1'
1%
#105000000015000
1.
#105000000025000
1-
#105000000035000
1,
#105000000040000
0+
#105000000050000
b1000001 !
b1000001 2
#120000000000000
b1000001 "
b1000001 #
#120000000010000
0.
0,
#120000000015000
1+
#120000000020000
0-
#135000000000000
b1111010 "
b1111010 #
#135000000004000
b1011010 !
b1011010 2
#135000000005000
0(
0'
0%
1$
#135000000010000
10
b1111010 !
b1111010 2
#135000000020000
1-
#135000000030000
1,
#135000000035000
0+
#135000000045000
b1011010 !
b1011010 2
#150000000000000
b1000111 "
b1000111 #
#150000000004000
b1000111 !
b1000111 2
#150000000005000
1(
1'
0&
0$
#150000000010000
00
0,
#150000000015000
1+
#150000000020000
0-
#165000000000000
b1101101 "
b1101101 #
#165000000004000
b1001101 !
b1001101 2
#165000000005000
0'
1%
#165000000010000
1.
b1101101 !
b1101101 2
#165000000020000
1-
#165000000030000
1,
#165000000035000
0+
#165000000045000
b1001101 !
b1001101 2
#180000000000000
b10010010 "
b10010010 #
#180000000004000
b10010010 !
b10010010 2
#180000000005000
0*
1)
0(
1'
1&
0%
1$
#180000000010000
0.
0,
#180000000015000
1+
#180000000020000
0-
#195000000000000
b110000 "
b110000 #
#195000000004000
b10000 !
b10000 2
#195000000005000
1*
1%
#195000000010000
b110000 !
b110000 2
#210000000000000
b11001111 "
b11001111 #
#210000000004000
b11101111 !
b11101111 2
#210000000005000
0*
0)
1(
0'
0&
0%
0$
#210000000010000
b11001111 !
b11001111 2
#225000000000000
b111010 "
b111010 #
#225000000004000
b11010 !
b11010 2
#225000000005000
1*
1)
0(
1&
1$
#225000000010000
b111010 !
b111010 2
#240000000000000
b1111011 "
b1111011 #
#240000000004000
b1111011 !
b1111011 2
#240000000005000
0)
0$
#240000000010000
10
#240000000020000
1-
#240000000030000
1,
#240000000035000
0+
#240000000045000
b1011011 !
b1011011 2
#255000000000000
b10010100 "
b10010100 #
#255000000004000
b10010100 !
b10010100 2
#255000000005000
0*
1)
1'
0&
1%
1$
#255000000010000
00
0,
#255000000015000
1+
#255000000020000
0-
#270000000000000
b1111111 "
b1111111 #
#270000000004000
b1011111 !
b1011111 2
#270000000005000
1*
0)
0'
0%
0$
#270000000010000
b1111111 !
b1111111 2
